txhqueue
