Metadata-Version: 1.1
Name: txhqueue
Version: 0.2.16
Summary: Asynchonous hysteresis-queue implementation.
Home-page: https://github.com/DNPA/txhqueue
Author: Rob M
Author-email: pdftool@pirod.nl
License: BSD
Keywords: async hysteresis queue highwater lowwater
Platform: UNKNOWN
Classifier: Development Status :: 4 - Beta
Classifier: Intended Audience :: Developers
Classifier: Topic :: Software Development :: Libraries
Classifier: License :: OSI Approved :: BSD License
Classifier: Programming Language :: Python :: 3
Classifier: Operating System :: OS Independent
Classifier: Environment :: Other Environment
